pickerUI
