Metadata-Version: 1.0
Name: pickerUI
Version: 1.2.0
Summary: a library of menu ui
Home-page: https://github.com/mlpod/pickerUI
Author: Jiaoxuewei
Author-email: jovae@qq.com
License: MIT License
Keywords: pickerUI
Platform: any
